{"name": "VALESKA MURIEL ERAZO ALFARO", "rank": "CCM", "periods": {"2025-09_Publicado": {"flight_hours": 50.95, "flight_count": 14, "airport_turns": 1, "home_turns": 1, "free_days": 10, "white_days": 2, "vac_days": 0, "sick_days": 0, "oof_days": 0, "reva": 0, "clases": 0, "bloque_libre": 0, "dh": 1, "timeline": [{"date": "2025-09-01", "activity": "ASB1", "act_type": "TURNO_AEROPUERTO", "block_hours": 0.0, "dep": "SCL", "arv": "SCL"}, {"date": "2025-09-02", "activity": "LA609", "act_type": "VUELO", "block_hours": 3.92, "dep": "SCL", "arv": "GRU"}, {"date": "2025-09-03", "activity": "LA751", "act_type": "VUELO", "block_hours": 4.33, "dep": "GRU", "arv": "SCL"}, {"date": "2025-09-05", "activity": "DR", "act_type": "DIA_LIBRE_SOLICITADO", "block_hours": 0.0, "dep": "SCL", "arv": "SCL"}, {"date": "2025-09-06", "activity": "DR", "act_type": "DIA_LIBRE_SOLICITADO", "block_hours": 0.0, "dep": "SCL", "arv": "SCL"}, {"date": "2025-09-07", "activity": "DR", "act_type": "DIA_LIBRE_SOLICITADO", "block_hours": 0.0, "dep": "SCL", "arv": "SCL"}, {"date": "2025-09-08", "activity": "DR", "act_type": "DIA_LIBRE_SOLICITADO", "block_hours": 0.0, "dep": "SCL", "arv": "SCL"}, {"date": "2025-09-09", "activity": "LA609", "act_type": "VUELO", "block_hours": 3.92, "dep": "SCL", "arv": "GRU"}, {"date": "2025-09-10", "activity": "LA751", "act_type": "VUELO", "block_hours": 4.33, "dep": "GRU", "arv": "SCL"}, {"date": "2025-09-12", "activity": "LA762", "act_type": "VUELO", "block_hours": 3.92, "dep": "SCL", "arv": "GRU"}, {"date": "2025-09-13", "activity": "LA751", "act_type": "VUELO", "block_hours": 4.33, "dep": "GRU", "arv": "SCL"}, {"date": "2025-09-15", "activity": "HSB1", "act_type": "TURNO_DOMICILIO", "block_hours": 0.0, "dep": "SCL", "arv": "SCL"}, {"date": "2025-09-16", "activity": "B", "act_type": "DIA_BLANCO", "block_hours": 0.0, "dep": "SCL", "arv": "SCL"}, {"date": "2025-09-17", "activity": "DH", "act_type": "DH", "block_hours": 0.0, "dep": "SCL", "arv": "SCL"}, {"date": "2025-09-18", "activity": "DR", "act_type": "DIA_LIBRE_SOLICITADO", "block_hours": 0.0, "dep": "SCL", "arv": "SCL"}, {"date": "2025-09-19", "activity": "DR", "act_type": "DIA_LIBRE_SOLICITADO", "block_hours": 0.0, "dep": "SCL", "arv": "SCL"}, {"date": "2025-09-20", "activity": "DR", "act_type": "DIA_LIBRE_SOLICITADO", "block_hours": 0.0, "dep": "SCL", "arv": "SCL"}, {"date": "2025-09-21", "activity": "DR", "act_type": "DIA_LIBRE_SOLICITADO", "block_hours": 0.0, "dep": "SCL", "arv": "SCL"}, {"date": "2025-09-22", "activity": "LA520", "act_type": "VUELO", "block_hours": 3.83, "dep": "SCL", "arv": "LIM"}, {"date": "2025-09-23", "activity": "LA651", "act_type": "VUELO", "block_hours": 3.58, "dep": "LIM", "arv": "SCL"}, {"date": "2025-09-23", "activity": "LA522", "act_type": "VUELO", "block_hours": 3.83, "dep": "SCL", "arv": "LIM"}, {"date": "2025-09-24", "activity": "LA521", "act_type": "VUELO", "block_hours": 3.58, "dep": "LIM", "arv": "SCL"}, {"date": "2025-09-25", "activity": "B", "act_type": "DIA_BLANCO", "block_hours": 0.0, "dep": "SCL", "arv": "SCL"}, {"date": "2025-09-26", "activity": "LA492", "act_type": "VUELO", "block_hours": 1.57, "dep": "SCL", "arv": "COR"}, {"date": "2025-09-26", "activity": "LA491", "act_type": "VUELO", "block_hours": 1.55, "dep": "COR", "arv": "SCL"}, {"date": "2025-09-26", "activity": "LA748", "act_type": "VUELO", "block_hours": 3.92, "dep": "SCL", "arv": "GRU"}, {"date": "2025-09-27", "activity": "LA755", "act_type": "VUELO", "block_hours": 4.33, "dep": "GRU", "arv": "SCL"}, {"date": "2025-09-29", "activity": "DO", "act_type": "DIA_LIBRE", "block_hours": 0.0, "dep": "SCL", "arv": "SCL"}, {"date": "2025-09-30", "activity": "DO", "act_type": "DIA_LIBRE", "block_hours": 0.0, "dep": "SCL", "arv": "SCL"}]}, "2025-10_Publicado": {"flight_hours": 58.07, "flight_count": 21, "airport_turns": 0, "home_turns": 0, "free_days": 0, "white_days": 0, "vac_days": 0, "sick_days": 0, "oof_days": 0, "reva": 0, "clases": 0, "bloque_libre": 0, "dh": 0, "timeline": [{"date": "2025-10-03", "activity": "LA073", "act_type": "VUELO", "block_hours": 2.35, "dep": "SCL", "arv": "BBA"}, {"date": "2025-10-03", "activity": "LA078", "act_type": "VUELO", "block_hours": 1.7, "dep": "PMC", "arv": "SCL"}, {"date": "2025-10-04", "activity": "LA762", "act_type": "VUELO", "block_hours": 3.92, "dep": "SCL", "arv": "GRU"}, {"date": "2025-10-05", "activity": "LA610", "act_type": "VUELO", "block_hours": 4.25, "dep": "GRU", "arv": "SCL"}, {"date": "2025-10-07", "activity": "LA155", "act_type": "VUELO", "block_hours": 2.05, "dep": "CJC", "arv": "SCL"}, {"date": "2025-10-07", "activity": "LA348", "act_type": "VUELO", "block_hours": 2.17, "dep": "SCL", "arv": "ANF"}, {"date": "2025-10-07", "activity": "LA152", "act_type": "VUELO", "block_hours": 2.13, "dep": "SCL", "arv": "CJC"}, {"date": "2025-10-08", "activity": "LA135", "act_type": "VUELO", "block_hours": 1.88, "dep": "ANF", "arv": "SCL"}, {"date": "2025-10-08", "activity": "LA902", "act_type": "VUELO", "block_hours": 2.42, "dep": "SCL", "arv": "IQQ"}, {"date": "2025-10-08", "activity": "LA913", "act_type": "VUELO", "block_hours": 2.25, "dep": "IQQ", "arv": "SCL"}, {"date": "2025-10-09", "activity": "LA108", "act_type": "VUELO", "block_hours": 1.13, "dep": "SCL", "arv": "LSC"}, {"date": "2025-10-09", "activity": "LA105", "act_type": "VUELO", "block_hours": 0.92, "dep": "LSC", "arv": "SCL"}, {"date": "2025-10-17", "activity": "LA762", "act_type": "VUELO", "block_hours": 3.92, "dep": "SCL", "arv": "GRU"}, {"date": "2025-10-18", "activity": "LA610", "act_type": "VUELO", "block_hours": 4.33, "dep": "GRU", "arv": "SCL"}, {"date": "2025-10-22", "activity": "LA762", "act_type": "VUELO", "block_hours": 3.92, "dep": "SCL", "arv": "GRU"}, {"date": "2025-10-23", "activity": "LA751", "act_type": "VUELO", "block_hours": 4.33, "dep": "GRU", "arv": "SCL"}, {"date": "2025-10-26", "activity": "LA176", "act_type": "VUELO", "block_hours": 2.38, "dep": "SCL", "arv": "IQQ"}, {"date": "2025-10-26", "activity": "LA177", "act_type": "VUELO", "block_hours": 2.22, "dep": "IQQ", "arv": "SCL"}, {"date": "2025-10-26", "activity": "LA284", "act_type": "VUELO", "block_hours": 1.72, "dep": "PMC", "arv": "SCL"}, {"date": "2025-10-28", "activity": "LA762", "act_type": "VUELO", "block_hours": 3.83, "dep": "SCL", "arv": "GRU"}, {"date": "2025-10-29", "activity": "LA758", "act_type": "VUELO", "block_hours": 4.25, "dep": "GRU", "arv": "SCL"}]}, "2025-11_Publicado": {"flight_hours": 52.87, "flight_count": 22, "airport_turns": 0, "home_turns": 1, "free_days": 14, "white_days": 2, "vac_days": 0, "sick_days": 0, "oof_days": 0, "reva": 0, "clases": 0, "bloque_libre": 15, "dh": 0, "timeline": [{"date": "2025-10-01", "activity": "DO", "act_type": "DIA_LIBRE", "block_hours": 0.0, "dep": "SCL", "arv": "SCL"}, {"date": "2025-10-02", "activity": "DO", "act_type": "DIA_LIBRE", "block_hours": 0.0, "dep": "SCL", "arv": "SCL"}, {"date": "2025-10-10", "activity": "B", "act_type": "DIA_BLANCO", "block_hours": 0.0, "dep": "SCL", "arv": "SCL"}, {"date": "2025-10-11", "activity": "DO", "act_type": "DIA_LIBRE", "block_hours": 0.0, "dep": "SCL", "arv": "SCL"}, {"date": "2025-10-12", "activity": "DO", "act_type": "DIA_LIBRE", "block_hours": 0.0, "dep": "SCL", "arv": "SCL"}, {"date": "2025-10-13", "activity": "DO", "act_type": "DIA_LIBRE", "block_hours": 0.0, "dep": "SCL", "arv": "SCL"}, {"date": "2025-10-14", "activity": "DO", "act_type": "DIA_LIBRE", "block_hours": 0.0, "dep": "SCL", "arv": "SCL"}, {"date": "2025-10-15", "activity": "HSB2", "act_type": "TURNO_DOMICILIO", "block_hours": 0.0, "dep": "SCL", "arv": "SCL"}, {"date": "2025-10-16", "activity": "B", "act_type": "DIA_BLANCO", "block_hours": 0.0, "dep": "SCL", "arv": "SCL"}, {"date": "2025-10-20", "activity": "DO", "act_type": "DIA_LIBRE", "block_hours": 0.0, "dep": "SCL", "arv": "SCL"}, {"date": "2025-10-21", "activity": "DO", "act_type": "DIA_LIBRE", "block_hours": 0.0, "dep": "SCL", "arv": "SCL"}, {"date": "2025-10-25", "activity": "LA071", "act_type": "VUELO", "block_hours": 2.42, "dep": "SCL", "arv": "BBA"}, {"date": "2025-10-25", "activity": "LA063", "act_type": "VUELO", "block_hours": 1.82, "dep": "SCL", "arv": "PMC"}, {"date": "2025-10-25", "activity": "LA070", "act_type": "VUELO", "block_hours": 2.3, "dep": "BBA", "arv": "SCL"}, {"date": "2025-10-30", "activity": "DR", "act_type": "DIA_LIBRE_SOLICITADO", "block_hours": 0.0, "dep": "SCL", "arv": "SCL"}, {"date": "2025-10-31", "activity": "DR", "act_type": "DIA_LIBRE_SOLICITADO", "block_hours": 0.0, "dep": "SCL", "arv": "SCL"}, {"date": "2025-11-01", "activity": "Q", "act_type": "BLOQUE_LIBRE", "block_hours": 0.0, "dep": "SCL", "arv": "SCL"}, {"date": "2025-11-02", "activity": "Q", "act_type": "BLOQUE_LIBRE", "block_hours": 0.0, "dep": "SCL", "arv": "SCL"}, {"date": "2025-11-03", "activity": "Q", "act_type": "BLOQUE_LIBRE", "block_hours": 0.0, "dep": "SCL", "arv": "SCL"}, {"date": "2025-11-04", "activity": "Q", "act_type": "BLOQUE_LIBRE", "block_hours": 0.0, "dep": "SCL", "arv": "SCL"}, {"date": "2025-11-05", "activity": "Q", "act_type": "BLOQUE_LIBRE", "block_hours": 0.0, "dep": "SCL", "arv": "SCL"}, {"date": "2025-11-06", "activity": "Q", "act_type": "BLOQUE_LIBRE", "block_hours": 0.0, "dep": "SCL", "arv": "SCL"}, {"date": "2025-11-07", "activity": "Q", "act_type": "BLOQUE_LIBRE", "block_hours": 0.0, "dep": "SCL", "arv": "SCL"}, {"date": "2025-11-08", "activity": "Q", "act_type": "BLOQUE_LIBRE", "block_hours": 0.0, "dep": "SCL", "arv": "SCL"}, {"date": "2025-11-09", "activity": "Q", "act_type": "BLOQUE_LIBRE", "block_hours": 0.0, "dep": "SCL", "arv": "SCL"}, {"date": "2025-11-10", "activity": "Q", "act_type": "BLOQUE_LIBRE", "block_hours": 0.0, "dep": "SCL", "arv": "SCL"}, {"date": "2025-11-11", "activity": "Q", "act_type": "BLOQUE_LIBRE", "block_hours": 0.0, "dep": "SCL", "arv": "SCL"}, {"date": "2025-11-12", "activity": "Q", "act_type": "BLOQUE_LIBRE", "block_hours": 0.0, "dep": "SCL", "arv": "SCL"}, {"date": "2025-11-13", "activity": "Q", "act_type": "BLOQUE_LIBRE", "block_hours": 0.0, "dep": "SCL", "arv": "SCL"}, {"date": "2025-11-14", "activity": "Q", "act_type": "BLOQUE_LIBRE", "block_hours": 0.0, "dep": "SCL", "arv": "SCL"}, {"date": "2025-11-15", "activity": "Q", "act_type": "BLOQUE_LIBRE", "block_hours": 0.0, "dep": "SCL", "arv": "SCL"}, {"date": "2025-11-16", "activity": "LA069", "act_type": "VUELO", "block_hours": 1.92, "dep": "SCL", "arv": "MHC"}, {"date": "2025-11-16", "activity": "LA363", "act_type": "VUELO", "block_hours": 1.85, "dep": "ANF", "arv": "SCL"}, {"date": "2025-11-16", "activity": "LA068", "act_type": "VUELO", "block_hours": 1.77, "dep": "MHC", "arv": "SCL"}, {"date": "2025-11-16", "activity": "LA362", "act_type": "VUELO", "block_hours": 2.0, "dep": "SCL", "arv": "ANF"}, {"date": "2025-11-17", "activity": "LA173", "act_type": "VUELO", "block_hours": 2.22, "dep": "IQQ", "arv": "SCL"}, {"date": "2025-11-17", "activity": "LA172", "act_type": "VUELO", "block_hours": 2.4, "dep": "SCL", "arv": "IQQ"}, {"date": "2025-11-19", "activity": "LA269", "act_type": "VUELO", "block_hours": 1.72, "dep": "SCL", "arv": "PMC"}, {"date": "2025-11-19", "activity": "LA268", "act_type": "VUELO", "block_hours": 1.72, "dep": "PMC", "arv": "SCL"}, {"date": "2025-11-20", "activity": "DO", "act_type": "DIA_LIBRE", "block_hours": 0.0, "dep": "SCL", "arv": "SCL"}, {"date": "2025-11-21", "activity": "DO", "act_type": "DIA_LIBRE", "block_hours": 0.0, "dep": "SCL", "arv": "SCL"}, {"date": "2025-11-22", "activity": "LA636", "act_type": "VUELO", "block_hours": 4.0, "dep": "SCL", "arv": "GRU"}, {"date": "2025-11-23", "activity": "LA636", "act_type": "VUELO", "block_hours": 3.0, "dep": "GRU", "arv": "EZE"}, {"date": "2025-11-24", "activity": "LA2445", "act_type": "VUELO", "block_hours": 2.25, "dep": "AEP", "arv": "SCL"}, {"date": "2025-11-25", "activity": "DO", "act_type": "DIA_LIBRE", "block_hours": 0.0, "dep": "SCL", "arv": "SCL"}, {"date": "2025-11-26", "activity": "DO", "act_type": "DIA_LIBRE", "block_hours": 0.0, "dep": "SCL", "arv": "SCL"}, {"date": "2025-11-27", "activity": "LA651", "act_type": "VUELO", "block_hours": 3.58, "dep": "LIM", "arv": "SCL"}, {"date": "2025-11-27", "activity": "LA650", "act_type": "VUELO", "block_hours": 3.83, "dep": "SCL", "arv": "LIM"}, {"date": "2025-11-28", "activity": "LA398", "act_type": "VUELO", "block_hours": 2.52, "dep": "CCP", "arv": "CJC"}, {"date": "2025-11-28", "activity": "LA212", "act_type": "VUELO", "block_hours": 1.13, "dep": "CCP", "arv": "SCL"}, {"date": "2025-11-28", "activity": "LA205", "act_type": "VUELO", "block_hours": 1.1, "dep": "SCL", "arv": "CCP"}, {"date": "2025-11-28", "activity": "LA399", "act_type": "VUELO", "block_hours": 2.53, "dep": "CJC", "arv": "CCP"}, {"date": "2025-11-29", "activity": "LA095", "act_type": "VUELO", "block_hours": 3.4, "dep": "SCL", "arv": "PUQ"}, {"date": "2025-11-29", "activity": "LA094", "act_type": "VUELO", "block_hours": 3.4, "dep": "PUQ", "arv": "SCL"}]}, "2025-12_Publicado": {"flight_hours": 14.05, "flight_count": 6, "airport_turns": 0, "home_turns": 2, "free_days": 5, "white_days": 3, "vac_days": 0, "sick_days": 0, "oof_days": 0, "reva": 0, "clases": 0, "bloque_libre": 0, "dh": 0, "timeline": [{"date": "2025-12-01", "activity": "B", "act_type": "DIA_BLANCO", "block_hours": 0.0, "dep": "SCL", "arv": "SCL"}, {"date": "2025-12-02", "activity": "HSB1", "act_type": "TURNO_DOMICILIO", "block_hours": 0.0, "dep": "SCL", "arv": "SCL"}, {"date": "2025-12-03", "activity": "HSB1", "act_type": "TURNO_DOMICILIO", "block_hours": 0.0, "dep": "SCL", "arv": "SCL"}, {"date": "2025-12-04", "activity": "B", "act_type": "DIA_BLANCO", "block_hours": 0.0, "dep": "SCL", "arv": "SCL"}, {"date": "2025-12-05", "activity": "DO", "act_type": "DIA_LIBRE", "block_hours": 0.0, "dep": "SCL", "arv": "SCL"}, {"date": "2025-12-06", "activity": "DO", "act_type": "DIA_LIBRE", "block_hours": 0.0, "dep": "SCL", "arv": "SCL"}, {"date": "2025-12-07", "activity": "DO", "act_type": "DIA_LIBRE", "block_hours": 0.0, "dep": "SCL", "arv": "SCL"}, {"date": "2025-12-08", "activity": "DO", "act_type": "DIA_LIBRE", "block_hours": 0.0, "dep": "SCL", "arv": "SCL"}, {"date": "2025-12-09", "activity": "LA178", "act_type": "VUELO", "block_hours": 2.38, "dep": "SCL", "arv": "IQQ"}, {"date": "2025-12-09", "activity": "LA179", "act_type": "VUELO", "block_hours": 2.22, "dep": "IQQ", "arv": "SCL"}, {"date": "2025-12-10", "activity": "LA628", "act_type": "VUELO", "block_hours": 2.05, "dep": "SCL", "arv": "EZE"}, {"date": "2025-12-11", "activity": "LA476", "act_type": "VUELO", "block_hours": 2.27, "dep": "EZE", "arv": "SCL"}, {"date": "2025-12-12", "activity": "B", "act_type": "DIA_BLANCO", "block_hours": 0.0, "dep": "SCL", "arv": "SCL"}, {"date": "2025-12-13", "activity": "LA082", "act_type": "VUELO", "block_hours": 3.4, "dep": "PUQ", "arv": "SCL"}, {"date": "2025-12-13", "activity": "LA311", "act_type": "VUELO", "block_hours": 1.73, "dep": "SCL", "arv": "PMC"}, {"date": "2025-12-14", "activity": "DO", "act_type": "DIA_LIBRE", "block_hours": 0.0, "dep": "SCL", "arv": "SCL"}]}, "2026-01_Publicado": {"flight_hours": 67.25, "flight_count": 22, "airport_turns": 0, "home_turns": 2, "free_days": 12, "white_days": 1, "vac_days": 0, "sick_days": 0, "oof_days": 0, "reva": 0, "clases": 0, "bloque_libre": 0, "dh": 0, "timeline": [{"date": "2026-01-01", "activity": "LA650", "act_type": "VUELO", "block_hours": 3.83, "dep": "SCL", "arv": "LIM"}, {"date": "2026-01-01", "activity": "LA651", "act_type": "VUELO", "block_hours": 3.58, "dep": "LIM", "arv": "SCL"}, {"date": "2026-01-02", "activity": "DR", "act_type": "DIA_LIBRE_SOLICITADO", "block_hours": 0.0, "dep": "SCL", "arv": "SCL"}, {"date": "2026-01-03", "activity": "DR", "act_type": "DIA_LIBRE_SOLICITADO", "block_hours": 0.0, "dep": "SCL", "arv": "SCL"}, {"date": "2026-01-04", "activity": "DR", "act_type": "DIA_LIBRE_SOLICITADO", "block_hours": 0.0, "dep": "SCL", "arv": "SCL"}, {"date": "2026-01-05", "activity": "DR", "act_type": "DIA_LIBRE_SOLICITADO", "block_hours": 0.0, "dep": "SCL", "arv": "SCL"}, {"date": "2026-01-06", "activity": "LA001", "act_type": "VUELO", "block_hours": 3.25, "dep": "SCL", "arv": "PNT"}, {"date": "2026-01-06", "activity": "LA002", "act_type": "VUELO", "block_hours": 3.12, "dep": "PNT", "arv": "SCL"}, {"date": "2026-01-07", "activity": "LA609", "act_type": "VUELO", "block_hours": 3.83, "dep": "SCL", "arv": "GRU"}, {"date": "2026-01-08", "activity": "LA751", "act_type": "VUELO", "block_hours": 4.25, "dep": "GRU", "arv": "SCL"}, {"date": "2026-01-10", "activity": "LA253", "act_type": "VUELO", "block_hours": 3.25, "dep": "SCL", "arv": "PNT"}, {"date": "2026-01-10", "activity": "LA254", "act_type": "VUELO", "block_hours": 3.12, "dep": "PNT", "arv": "SCL"}, {"date": "2026-01-11", "activity": "LA112", "act_type": "VUELO", "block_hours": 1.52, "dep": "SCL", "arv": "CPO"}, {"date": "2026-01-11", "activity": "LA113", "act_type": "VUELO", "block_hours": 1.27, "dep": "CPO", "arv": "SCL"}, {"date": "2026-01-11", "activity": "LA750", "act_type": "VUELO", "block_hours": 3.92, "dep": "SCL", "arv": "GRU"}, {"date": "2026-01-12", "activity": "LA751", "act_type": "VUELO", "block_hours": 4.25, "dep": "GRU", "arv": "SCL"}, {"date": "2026-01-14", "activity": "DO", "act_type": "DIA_LIBRE", "block_hours": 0.0, "dep": "SCL", "arv": "SCL"}, {"date": "2026-01-15", "activity": "DO", "act_type": "DIA_LIBRE", "block_hours": 0.0, "dep": "SCL", "arv": "SCL"}, {"date": "2026-01-16", "activity": "DO", "act_type": "DIA_LIBRE", "block_hours": 0.0, "dep": "SCL", "arv": "SCL"}, {"date": "2026-01-17", "activity": "DO", "act_type": "DIA_LIBRE", "block_hours": 0.0, "dep": "SCL", "arv": "SCL"}, {"date": "2026-01-18", "activity": "HSB1", "act_type": "TURNO_DOMICILIO", "block_hours": 0.0, "dep": "SCL", "arv": "SCL"}, {"date": "2026-01-19", "activity": "B", "act_type": "DIA_BLANCO", "block_hours": 0.0, "dep": "SCL", "arv": "SCL"}, {"date": "2026-01-20", "activity": "LA114", "act_type": "VUELO", "block_hours": 1.52, "dep": "SCL", "arv": "CPO"}, {"date": "2026-01-20", "activity": "LA115", "act_type": "VUELO", "block_hours": 1.27, "dep": "CPO", "arv": "SCL"}, {"date": "2026-01-20", "activity": "LA750", "act_type": "VUELO", "block_hours": 3.92, "dep": "SCL", "arv": "GRU"}, {"date": "2026-01-21", "activity": "LA751", "act_type": "VUELO", "block_hours": 4.25, "dep": "GRU", "arv": "SCL"}, {"date": "2026-01-23", "activity": "LA750", "act_type": "VUELO", "block_hours": 3.92, "dep": "SCL", "arv": "GRU"}, {"date": "2026-01-23", "activity": "LA435", "act_type": "VUELO", "block_hours": 0.93, "dep": "MDZ", "arv": "SCL"}, {"date": "2026-01-23", "activity": "LA434", "act_type": "VUELO", "block_hours": 1.08, "dep": "SCL", "arv": "MDZ"}, {"date": "2026-01-24", "activity": "LA751", "act_type": "VUELO", "block_hours": 4.25, "dep": "GRU", "arv": "SCL"}, {"date": "2026-01-26", "activity": "DO", "act_type": "DIA_LIBRE", "block_hours": 0.0, "dep": "SCL", "arv": "SCL"}, {"date": "2026-01-27", "activity": "DO", "act_type": "DIA_LIBRE", "block_hours": 0.0, "dep": "SCL", "arv": "SCL"}, {"date": "2026-01-28", "activity": "DO", "act_type": "DIA_LIBRE", "block_hours": 0.0, "dep": "SCL", "arv": "SCL"}, {"date": "2026-01-29", "activity": "DO", "act_type": "DIA_LIBRE", "block_hours": 0.0, "dep": "SCL", "arv": "SCL"}, {"date": "2026-01-30", "activity": "LA510", "act_type": "VUELO", "block_hours": 3.3, "dep": "SCL", "arv": "FLN"}, {"date": "2026-01-30", "activity": "LA511", "act_type": "VUELO", "block_hours": 3.63, "dep": "FLN", "arv": "SCL"}, {"date": "2026-01-31", "activity": "HSB2", "act_type": "TURNO_DOMICILIO", "block_hours": 0.0, "dep": "SCL", "arv": "SCL"}]}, "2026-02_Publicado": {"flight_hours": 59.87, "flight_count": 26, "airport_turns": 1, "home_turns": 2, "free_days": 9, "white_days": 2, "vac_days": 0, "sick_days": 0, "oof_days": 0, "reva": 0, "clases": 0, "bloque_libre": 0, "dh": 1, "timeline": [{"date": "2026-02-01", "activity": "B", "act_type": "DIA_BLANCO", "block_hours": 0.0, "dep": "SCL", "arv": "SCL"}, {"date": "2026-02-02", "activity": "LA132", "act_type": "VUELO", "block_hours": 1.98, "dep": "SCL", "arv": "ANF"}, {"date": "2026-02-02", "activity": "LA135", "act_type": "VUELO", "block_hours": 1.8, "dep": "ANF", "arv": "SCL"}, {"date": "2026-02-02", "activity": "LA316", "act_type": "VUELO", "block_hours": 1.12, "dep": "SCL", "arv": "LSC"}, {"date": "2026-02-02", "activity": "LA317", "act_type": "VUELO", "block_hours": 0.93, "dep": "LSC", "arv": "SCL"}, {"date": "2026-02-03", "activity": "DO", "act_type": "DIA_LIBRE", "block_hours": 0.0, "dep": "SCL", "arv": "SCL"}, {"date": "2026-02-04", "activity": "DO", "act_type": "DIA_LIBRE", "block_hours": 0.0, "dep": "SCL", "arv": "SCL"}, {"date": "2026-02-05", "activity": "LA435", "act_type": "VUELO", "block_hours": 0.93, "dep": "MDZ", "arv": "SCL"}, {"date": "2026-02-05", "activity": "LA750", "act_type": "VUELO", "block_hours": 3.92, "dep": "SCL", "arv": "GRU"}, {"date": "2026-02-05", "activity": "LA434", "act_type": "VUELO", "block_hours": 1.08, "dep": "SCL", "arv": "MDZ"}, {"date": "2026-02-06", "activity": "LA751", "act_type": "VUELO", "block_hours": 4.17, "dep": "GRU", "arv": "SCL"}, {"date": "2026-02-08", "activity": "ASB1", "act_type": "TURNO_AEROPUERTO", "block_hours": 0.0, "dep": "SCL", "arv": "SCL"}, {"date": "2026-02-09", "activity": "HSB1", "act_type": "TURNO_DOMICILIO", "block_hours": 0.0, "dep": "SCL", "arv": "SCL"}, {"date": "2026-02-10", "activity": "HSB1", "act_type": "TURNO_DOMICILIO", "block_hours": 0.0, "dep": "SCL", "arv": "SCL"}, {"date": "2026-02-11", "activity": "B", "act_type": "DIA_BLANCO", "block_hours": 0.0, "dep": "SCL", "arv": "SCL"}, {"date": "2026-02-12", "activity": "LA097", "act_type": "VUELO", "block_hours": 3.38, "dep": "SCL", "arv": "PUQ"}, {"date": "2026-02-12", "activity": "LA092", "act_type": "VUELO", "block_hours": 3.4, "dep": "PUQ", "arv": "SCL"}, {"date": "2026-02-13", "activity": "DO", "act_type": "DIA_LIBRE", "block_hours": 0.0, "dep": "SCL", "arv": "SCL"}, {"date": "2026-02-14", "activity": "DO", "act_type": "DIA_LIBRE", "block_hours": 0.0, "dep": "SCL", "arv": "SCL"}, {"date": "2026-02-15", "activity": "DO", "act_type": "DIA_LIBRE", "block_hours": 0.0, "dep": "SCL", "arv": "SCL"}, {"date": "2026-02-16", "activity": "DO", "act_type": "DIA_LIBRE", "block_hours": 0.0, "dep": "SCL", "arv": "SCL"}, {"date": "2026-02-17", "activity": "DH", "act_type": "DH", "block_hours": 0.0, "dep": "SCL", "arv": "SCL"}, {"date": "2026-02-18", "activity": "LA762", "act_type": "VUELO", "block_hours": 3.83, "dep": "SCL", "arv": "GRU"}, {"date": "2026-02-19", "activity": "LA751", "act_type": "VUELO", "block_hours": 4.17, "dep": "GRU", "arv": "SCL"}, {"date": "2026-02-21", "activity": "LA069", "act_type": "VUELO", "block_hours": 1.93, "dep": "SCL", "arv": "MHC"}, {"date": "2026-02-21", "activity": "LA068", "act_type": "VUELO", "block_hours": 1.77, "dep": "MHC", "arv": "SCL"}, {"date": "2026-02-21", "activity": "LA338", "act_type": "VUELO", "block_hours": 1.47, "dep": "SCL", "arv": "CPO"}, {"date": "2026-02-21", "activity": "LA337", "act_type": "VUELO", "block_hours": 1.25, "dep": "CPO", "arv": "SCL"}, {"date": "2026-02-22", "activity": "LA363", "act_type": "VUELO", "block_hours": 1.78, "dep": "ANF", "arv": "SCL"}, {"date": "2026-02-22", "activity": "LA362", "act_type": "VUELO", "block_hours": 2.02, "dep": "SCL", "arv": "ANF"}, {"date": "2026-02-22", "activity": "LA114", "act_type": "VUELO", "block_hours": 1.47, "dep": "SCL", "arv": "CPO"}, {"date": "2026-02-22", "activity": "LA119", "act_type": "VUELO", "block_hours": 1.25, "dep": "CPO", "arv": "SCL"}, {"date": "2026-02-23", "activity": "DO", "act_type": "DIA_LIBRE", "block_hours": 0.0, "dep": "SCL", "arv": "SCL"}, {"date": "2026-02-24", "activity": "DO", "act_type": "DIA_LIBRE", "block_hours": 0.0, "dep": "SCL", "arv": "SCL"}, {"date": "2026-02-25", "activity": "DO", "act_type": "DIA_LIBRE", "block_hours": 0.0, "dep": "SCL", "arv": "SCL"}, {"date": "2026-02-26", "activity": "LA328", "act_type": "VUELO", "block_hours": 1.47, "dep": "SCL", "arv": "CPO"}, {"date": "2026-02-26", "activity": "LA115", "act_type": "VUELO", "block_hours": 1.25, "dep": "CPO", "arv": "SCL"}, {"date": "2026-02-26", "activity": "LA630", "act_type": "VUELO", "block_hours": 4.0, "dep": "SCL", "arv": "GRU"}, {"date": "2026-02-27", "activity": "LA763", "act_type": "VUELO", "block_hours": 2.67, "dep": "MVD", "arv": "GRU"}, {"date": "2026-02-27", "activity": "LA762", "act_type": "VUELO", "block_hours": 2.67, "dep": "GRU", "arv": "MVD"}, {"date": "2026-02-28", "activity": "LA751", "act_type": "VUELO", "block_hours": 4.17, "dep": "GRU", "arv": "SCL"}]}, "2026-03_Publicado": {"flight_hours": 0.0, "flight_count": 0, "airport_turns": 0, "home_turns": 0, "free_days": 1, "white_days": 0, "vac_days": 0, "sick_days": 0, "oof_days": 0, "reva": 0, "clases": 0, "bloque_libre": 0, "dh": 0, "timeline": [{"date": "2026-03-02", "activity": "DO", "act_type": "DIA_LIBRE", "block_hours": 0.0, "dep": "SCL", "arv": "SCL"}]}}}